aksyx.so
aksui/__init__.py
aksui/ak.py.glade
aksui/browser.py
aksui/gtkexcepthook.py
aksui/main.py
aksui/treemain.py
aksui/UI/__init__.py
aksui/UI/base.py
aksui/UI/editors.py
aksui/UI/envelopewidget.py
aksui/UI/filechooser.py
aksui/UI/filterpanel.py
aksui/UI/hitbox.py
aksui/UI/keygroupdetails.py
aksui/UI/keygroupeditor.py
aksui/UI/keygroupeditor_old.py
aksui/UI/keygroupenvelope.py
aksui/UI/keygroupfilter.py
aksui/UI/keygrouppanel.py
aksui/UI/lcdscreen.py
aksui/UI/lfopanel.py
aksui/UI/modmatrix.py
aksui/UI/multieditor.py
aksui/UI/multifxeditor.py
aksui/UI/panelbase.py
aksui/UI/programdetails.py
aksui/UI/rangewidget.py
aksui/UI/recorddialog.py
aksui/UI/widget.py
aksui/UI/zonepanel.py
aksui/ak/__init__.py
aksui/ak/envelope.py
aksui/ak/keygroup.py
aksui/ak/lfo.py
aksui/ak/modulationmatrix.py
aksui/ak/modulationpin.py
aksui/ak/multi.py
aksui/ak/multifx.py
aksui/ak/part.py
aksui/ak/program.py
aksui/ak/programs.py
aksui/ak/recording.py
aksui/ak/samplerobject.py
aksui/ak/samples.py
aksui/ak/zone.py
aksui/utils/__init__.py
aksui/utils/midiutils.py
aksui/utils/modelutils.py
aksui/utils/sox.py
aksy/__init__.py
aksy/concurrent.py
aksy/config.py
aksy/device.py
aksy/fileutils.py
aksy/console/__init__.py
aksy/console/get.py
aksy/console/put.py
aksy/devices/__init__.py
aksy/devices/akai/__init__.py
aksy/devices/akai/connector.py
aksy/devices/akai/filebuilder.py
aksy/devices/akai/filemodel.py
aksy/devices/akai/fileparser.py
aksy/devices/akai/model.py
aksy/devices/akai/sampler.py
aksy/devices/akai/sysex.py
aksy/devices/akai/sysex_types.py
aksy/devices/akai/transfertools.py
aksy/devices/akai/mock_z48/__init__.py
aksy/devices/akai/mock_z48/sampler.py
aksy/devices/akai/s56k/__init__.py
aksy/devices/akai/s56k/disktools.py
aksy/devices/akai/s56k/multitools.py
aksy/devices/akai/s56k/programtools.py
aksy/devices/akai/s56k/sampler.py
aksy/devices/akai/s56k/sampletools.py
aksy/devices/akai/s56k/songtools.py
aksy/devices/akai/s56k/sysextools.py
aksy/devices/akai/z48/__init__.py
aksy-0.4.dist-info/LICENSE.txt
aksy-0.4.dist-info/METADATA
aksy-0.4.dist-info/WHEEL
aksy-0.4.dist-info/dependency_links.txt
aksy-0.4.dist-info/entry_points.txt
aksy-0.4.dist-info/top_level.txt
aksy-0.4.dist-info/RECORD
